{
    "product_id": "dtdd_mobell-m539",
    "url": "https://thegioididong.com/dtdd/mobell-m539",
    "questions": [
      {
        "qa_id": "p_dtdd_mobell-m539_qa_00",
        "question": "Điện thoại Mobell M539 có mấy phiên bản màu sắc?",
        "question_type": "general information",
        "answer": "Điện thoại Mobell M539 có 3 phiên bản màu sắc là Đỏ, Vàng đồng, và Đen."
      },
      {
        "qa_id": "p_dtdd_mobell-m539_qa_01",
        "question": "Mức giá hiện tại của điện thoại Mobell M539 là bao nhiêu?",
        "question_type": "price",
        "answer": "Mức giá hiện tại của điện thoại Mobell M539 là 640.000₫."
      },
      {
        "qa_id": "p_dtdd_mobell-m539_qa_02",
        "question": "Điện thoại Mobell M539 có chính sách bảo hành như thế nào?",
        "question_type": "policies",
        "answer": "Điện thoại Mobell M539 được hỗ trợ hư gì đổi nấy trong 12 tháng tại 3158 siêu thị toàn quốc (miễn phí tháng đầu). Bảo hành chính hãng điện thoại 1 năm tại các trung tâm bảo hành hãng. Bộ sản phẩm bao gồm: Hộp, Pin, Sạc, Sách hướng dẫn."
      },
      {
        "qa_id": "p_dtdd_mobell-m539_qa_03",
        "question": "Điện thoại Mobell M539 có ưu đãi khuyến mãi nào áp dụng không?",
        "question_type": "promotion",
        "answer": "Điện thoại Mobell M539 được giảm giá 8% so với giá gốc, từ 700.000₫ xuống còn 640.000₫. Ngoài ra, nhập mã VNPAYTGDD2 giảm ngay 1% (tối đa 200.000đ) khi thanh toán qua VNPAY-QR, áp dụng cho đơn hàng từ 3 Triệu."
      },
      {
        "qa_id": "p_dtdd_mobell-m539_qa_04",
        "question": "Điện thoại Mobell M539 có khả năng quay phim không?",
        "question_type": "features and capabilities",
        "answer": "Có, điện thoại Mobell M539 có khả năng quay phim."
      },
      {
        "qa_id": "p_dtdd_mobell-m539_qa_05",
        "question": "Chip xử lý của điện thoại Mobell M539 là gì?",
        "question_type": "technical specifications",
        "answer": "Chip xử lý của điện thoại Mobell M539 là Unisoc T107."
      },
      {
        "qa_id": "p_dtdd_mobell-m539_qa_06",
        "question": "Camera sau của điện thoại Mobell M539 có độ phân giải bao nhiêu?",
        "question_type": "technical specifications",
        "answer": "Camera sau của điện thoại Mobell M539 có độ phân giải là 0.08 MP."
      },
      {
        "qa_id": "p_dtdd_mobell-m539_qa_07",
        "question": "RAM của điện thoại Mobell M539 có dung lượng bao nhiêu?",
        "question_type": "technical specifications",
        "answer": "RAM của điện thoại Mobell M539 có dung lượng là 48 MB."
      },
      {
        "qa_id": "p_dtdd_mobell-m539_qa_08",
        "question": "Dung lượng pin của điện thoại Mobell M539 là bao nhiêu?",
        "question_type": "technical specifications",
        "answer": "Dung lượng pin của điện thoại Mobell M539 là 2000 mAh."
      },
      {
        "qa_id": "p_dtdd_mobell-m539_qa_09",
        "question": "Kích thước và khối lượng của điện thoại Mobell M539 là gì?",
        "question_type": "technical specifications",
        "answer": "Kích thước của điện thoại Mobell M539 là Dài 130 mm - Ngang 55.5 mm - Dày 12.5 mm và nặng 130 g."
      },
      {
        "qa_id": "p_dtdd_mobell-m539_qa_10",
        "question": "Điện thoại Mobell M539 có hỗ trợ mạng di động nào?",
        "question_type": "technical specifications",
        "answer": "Điện thoại Mobell M539 hỗ trợ mạng di động 4G VoLTE."
      },
      {
        "qa_id": "p_dtdd_mobell-m539_qa_11",
        "question": "Sản phẩm đi kèm với điện thoại Mobell M539 bao gồm những gì?",
        "question_type": "general information",
        "answer": "Sản phẩm đi kèm với điện thoại Mobell M539 bao gồm Hộp, Pin, Sạc, Sách hướng dẫn."
      },
      {
        "qa_id": "p_dtdd_mobell-m539_qa_12",
        "question": "Điện thoại Mobell M539 được ra mắt vào thời điểm nào?",
        "question_type": "general information",
        "answer": "Điện thoại Mobell M539 được ra mắt vào tháng 9 năm 2022."
      },
      {
        "qa_id": "p_dtdd_mobell-m539_qa_13",
        "question": "Điện thoại Mobell M539 có ra mắt ở hãng nào?",
        "question_type": "general information",
        "answer": "Điện thoại Mobell M539 được ra mắt bởi Mobell."
      },
      {
        "qa_id": "p_dtdd_mobell-m539_qa_14",
        "question": "Điện thoại Mobell M539 có thể mở rộng bộ nhớ bằng thẻ nhớ tối đa bao nhiêu?",
        "question_type": "technical specifications",
        "answer": "Điện thoại Mobell M539 có thể mở rộng bộ nhớ bằng thẻ nhớ tối đa 64 GB."
      },
      {
        "qa_id": "p_dtdd_mobell-m539_qa_15",
        "question": "Điện thoại Mobell M539 có tính năng ghi âm không?",
        "question_type": "features and capabilities",
        "answer": "Có, điện thoại Mobell M539 có tính năng ghi âm mặc định và ghi âm cuộc gọi."
      },
      {
        "qa_id": "p_dtdd_mobell-m539_qa_16",
        "question": "Điện thoại Mobell M539 có tính năng xem phim dạng file nào?",
        "question_type": "features and capabilities",
        "answer": "Điện thoại Mobell M539 có tính năng xem phim dạng file 3GP."
      },
      {
        "qa_id": "p_dtdd_mobell-m539_qa_17",
        "question": "Điện thoại Mobell M539 có tính năng nghe nhạc không?",
        "question_type": "features and capabilities",
        "answer": "Có, điện thoại Mobell M539 có tính năng nghe nhạc định dạng file MP3."
      },
      {
        "qa_id": "p_dtdd_mobell-m539_qa_18",
        "question": "Điện thoại Mobell M539 có hỗ trợ SIM gì?",
        "question_type": "technical specifications",
        "answer": "Điện thoại Mobell M539 có hỗ trợ 2 Nano SIM."
      },
      {
        "qa_id": "p_dtdd_mobell-m539_qa_19",
        "question": "Điện thoại Mobell M539 có tính năng đèn pin không?",
        "question_type": "features and capabilities",
        "answer": "Có, điện thoại Mobell M539 có tính năng đèn pin."
      }
    ]
  }
  