{
    "product_id": "dtdd-nokia-105-4g",
    "url": "https://thegioididong.com/dtdd/nokia-105-4g",
    "questions": [
        {
            "qa_id": "p_dtdd-nokia-105-4g_qa_01",
            "question": "Điện thoại Nokia 105 có giá bao nhiêu?",
            "question_category": "thông tin chung",
            "short_answer": "650.000₫",
            "long_answer": "Điện thoại Nokia 105 hiện có giá là 650.000₫."
        },
        {
            "qa_id": "p_dtdd-nokia-105-4g_qa_02",
            "question": "Thiết kế của Điện thoại Nokia 105 như thế nào?",
            "question_category": "thông tin chung",
            "short_answer": "Pin rời, khung & mặt lưng nhựa",
            "long_answer": "Điện thoại Nokia 105 được thiết kế với pin rời và khung & mặt lưng nhựa."
        },
        {
            "qa_id": "p_dtdd-nokia-105-4g_qa_03",
            "question": "Điện thoại Nokia 105 có kích thước và khối lượng như thế nào?",
            "question_category": "thông tin chung",
            "short_answer": "Dài 121 mm - Ngang 50 mm - Dày 14.5 mm - Nặng 80.2 g",
            "long_answer": "Điện thoại Nokia 105 có kích thước: Dài 121 mm, Ngang 50 mm, Dày 14.5 mm và nặng 80.2 g."
        },
        {
            "qa_id": "p_dtdd-nokia-105-4g_qa_04",
            "question": "Màn hình của Điện thoại Nokia 105 có kích thước bao nhiêu inch?",
            "question_category": "thông số kỹ thuật",
            "short_answer": "1.8 inch",
            "long_answer": "Màn hình của Điện thoại Nokia 105 có kích thước 1.8 inch."
        },
        {
            "qa_id": "p_dtdd-nokia-105-4g_qa_05",
            "question": "Điện thoại Nokia 105 hỗ trợ mạng di động nào?",
            "question_category": "thông số kỹ thuật",
            "short_answer": "Hỗ trợ 4G VoLTE",
            "long_answer": "Điện thoại Nokia 105 hỗ trợ mạng di động 4G VoLTE."
        },
        {
            "qa_id": "p_dtdd-nokia-105-4g_qa_06",
            "question": "Dung lượng pin của Điện thoại Nokia 105 là bao nhiêu mAh?",
            "question_category": "thông số kỹ thuật",
            "short_answer": "1020 mAh",
            "long_answer": "Điện thoại Nokia 105 có dung lượng pin là 1020 mAh."
        },
        {
            "qa_id": "p_dtdd-nokia-105-4g_qa_07",
            "question": "Điện thoại Nokia 105 có tính năng đặc biệt nào?",
            "question_category": "tiện ích",
            "short_answer": "Chặn tin nhắn, chặn cuộc gọi",
            "long_answer": "Điện thoại Nokia 105 có tính năng đặc biệt là chặn tin nhắn và chặn cuộc gọi."
        },
        {
            "qa_id": "p_dtdd-nokia-105-4g_qa_08",
            "question": "Điện thoại Nokia 105 có bao nhiêu điểm đánh giá trung bình?",
            "question_category": "đánh giá",
            "short_answer": "3.6",
            "long_answer": "Điện thoại Nokia 105 có điểm đánh giá trung bình là 3.6."
        },
        {
            "qa_id": "p_dtdd-nokia-105-4g_qa_09",
            "question": "Điện thoại Nokia 105 có màn hình loại nào?",
            "question_category": "thông số kỹ thuật",
            "short_answer": "TFT LCD",
            "long_answer": "Điện thoại Nokia 105 có màn hình loại TFT LCD."
        },
        {
            "qa_id": "p_dtdd-nokia-105-4g_qa_10",
            "question": "Chip xử lý (CPU) của Điện thoại Nokia 105 là gì?",
            "question_category": "thông số kỹ thuật",
            "short_answer": "Unisoc T107",
            "long_answer": "Chip xử lý (CPU) của Điện thoại Nokia 105 là Unisoc T107."
        },
        {
            "qa_id": "p_dtdd-nokia-105-4g_qa_11",
            "question": "Dung lượng lưu trữ của Điện thoại Nokia 105 là bao nhiêu?",
            "question_category": "thông số kỹ thuật",
            "short_answer": "128 MB",
            "long_answer": "Dung lượng lưu trữ của Điện thoại Nokia 105 là 128 MB."
        },
        {
            "qa_id": "p_dtdd-nokia-105-4g_qa_12",
            "question": "Điện thoại Nokia 105 có tính năng đặc biệt nào khác ngoài chặn tin nhắn và chặn cuộc gọi?",
            "question_category": "tiện ích",
            "short_answer": "Radio FM không cần tai nghe, đèn pin, nghe nhạc MP3",
            "long_answer": "Điện thoại Nokia 105 có tính năng đặc biệt bao gồm radio FM không cần tai nghe, đèn pin và nghe nhạc MP3."
        },
        {
            "qa_id": "p_dtdd-nokia-105-4g_qa_13",
            "question": "Điện thoại Nokia 105 có bao nhiêu số lượng đánh giá?",
            "question_category": "đánh giá",
            "short_answer": "328",
            "long_answer": "Điện thoại Nokia 105 có tổng cộng 328 đánh giá."
        }
    ]
}